{
    "homepage": "https://wiki.mozilla.org/Add-ons/Extension_Signing#Unbranded_Builds",
    "version": "106_0_1",
    "license": "MPL-2.0",
    "architecture": {
        "64bit": {
            "url": "https://firefox-ci-tc.services.mozilla.com/api/index/v1/task/gecko.v2.mozilla-release.revision.4b58b98809817ef444fab57234d4702e4581320d.firefox.win64-add-on-devel/artifacts/public/build/target.zip",
            "hash": "91a67cb2319966738219473eeb27ed3c8b37816df364461140eb274947b682ba"
        },
        "32bit": {
            "url": "https://firefox-ci-tc.services.mozilla.com/api/index/v1/task/gecko.v2.mozilla-release.revision.4b58b98809817ef444fab57234d4702e4581320d.firefox.win32-add-on-devel/artifacts/public/build/target.zip",
            "hash": "a535c2b6cc32f5f46e5e1049888e9c80896bf206618cdbd34fb347d565565d9b"
        }
    },
    "extract_dir": "firefox",
    "pre_install": [
        "mkdir -f \"$dir\\distribution\" | Out-Null",
        "Set-Content \"$dir\\distribution\\policies.json\" '{\"policies\":{\"DisableAppUpdate\":true,\"DisableFirefoxStudies\":true,\"DisableSystemAddonUpdate\":true,\"DisableTelemetry\":true}}'"
    ],
    "persist": "distribution",
    "bin": [
        [
            "firefox.exe",
            "firefox-unbranded"
        ]
    ],
    "shortcuts": [
        [
            "firefox.exe",
            "Firefox Unbranded"
        ]
    ],
    "checkver": {
        "url": "https://hg.mozilla.org/releases/mozilla-release/raw-file/tip/.hgtags",
        "re": "\\b(?<revision>[0-9a-fA-F]{40}) FIREFOX_(?<version>[\\d_]+)_RELEASE\\b",
        "reverse": true
    },
    "autoupdate": {
        "architecture": {
            "64bit": {
                "url": "https://firefox-ci-tc.services.mozilla.com/api/index/v1/task/gecko.v2.mozilla-release.revision.$matchRevision.firefox.win64-add-on-devel/artifacts/public/build/target.zip"
            },
            "32bit": {
                "url": "https://firefox-ci-tc.services.mozilla.com/api/index/v1/task/gecko.v2.mozilla-release.revision.$matchRevision.firefox.win32-add-on-devel/artifacts/public/build/target.zip"
            }
        }
    }
}
